tekpower/__init__.py
tekpower/tekpower.py
tekpower-0.1.1.dist-info/METADATA
tekpower-0.1.1.dist-info/RECORD
tekpower-0.1.1.dist-info/WHEEL
tekpower-0.1.1.dist-info/top_level.txt
