Metadata-Version: 2.1
Name: tekpower
Version: 0.1.1
Summary: Hardware abstraction to USB controlled power supplies from Tekpower
Home-page: https://github.com/mgeiger/tekpower
Author: Matthew J. Geiger
Author-email: matthew.j.geiger@gmail.com
License: MIT license
Keywords: tekpower
Platform: UNKNOWN
Classifier: Development Status :: 2 - Pre-Alpha
Classifier: Intended Audience :: Developers
Classifier: License :: OSI Approved :: MIT License
Classifier: Natural Language :: English
Classifier: Programming Language :: Python :: 2
Classifier: Programming Language :: Python :: 2.7
Classifier: Programming Language :: Python :: 3
Classifier: Programming Language :: Python :: 3.4
Classifier: Programming Language :: Python :: 3.5
Classifier: Programming Language :: Python :: 3.6
